census_map_downloader/__init__.py
census_map_downloader/base.py
census_map_downloader/cli.py
census_map_downloader/geotypes/__init__.py
census_map_downloader/geotypes/blocks.py
census_map_downloader/geotypes/congress_carto.py
census_map_downloader/geotypes/counties.py
census_map_downloader/geotypes/counties_carto.py
census_map_downloader/geotypes/countysubdivision_carto.py
census_map_downloader/geotypes/legislativedistrict_lower_carto.py
census_map_downloader/geotypes/legislativedistrict_upper_carto.py
census_map_downloader/geotypes/places.py
census_map_downloader/geotypes/states_carto.py
census_map_downloader/geotypes/tracts.py
census_map_downloader/geotypes/zctas.py
census_map_downloader-0.1.3.dist-info/LICENSE
census_map_downloader-0.1.3.dist-info/METADATA
census_map_downloader-0.1.3.dist-info/WHEEL
census_map_downloader-0.1.3.dist-info/entry_points.txt
census_map_downloader-0.1.3.dist-info/top_level.txt
census_map_downloader-0.1.3.dist-info/RECORD
