Metadata-Version: 2.1
Name: census-map-downloader
Version: 0.1.3
Summary: Easily download U.S. census maps
Home-page: https://github.com/datadesk
License: MIT
Project-URL: Maintainer, https://github.com/datadesk
Project-URL: Source, https://github.com/datadesk/census-map-downloader
Project-URL: Tracker, https://github.com/datadesk/census-map-downloader/issues
Classifier: Development Status :: 5 - Production/Stable
Classifier: Programming Language :: Python
Classifier: Programming Language :: Python :: 3.7
Classifier: Programming Language :: Python :: 3.8
Classifier: Programming Language :: Python :: 3.9
Classifier: Programming Language :: Python :: 3.10
Classifier: Programming Language :: Python :: 3 :: Only
Classifier: License :: OSI Approved :: MIT License
License-File: LICENSE
Requires-Dist: geopandas
Requires-Dist: us
Requires-Dist: click
